stable_baselines/__init__.py
stable_baselines/logger.py
stable_baselines/py.typed
stable_baselines/results_plotter.py
stable_baselines/version.txt
stable_baselines/a2c/__init__.py
stable_baselines/a2c/a2c.py
stable_baselines/a2c/run_atari.py
stable_baselines/acer/__init__.py
stable_baselines/acer/acer_simple.py
stable_baselines/acer/buffer.py
stable_baselines/acer/run_atari.py
stable_baselines/acktr/__init__.py
stable_baselines/acktr/acktr.py
stable_baselines/acktr/kfac.py
stable_baselines/acktr/kfac_utils.py
stable_baselines/acktr/run_atari.py
stable_baselines/bench/__init__.py
stable_baselines/bench/monitor.py
stable_baselines/common/__init__.py
stable_baselines/common/atari_wrappers.py
stable_baselines/common/base_class.py
stable_baselines/common/bit_flipping_env.py
stable_baselines/common/buffers.py
stable_baselines/common/callbacks.py
stable_baselines/common/cg.py
stable_baselines/common/cmd_util.py
stable_baselines/common/console_util.py
stable_baselines/common/dataset.py
stable_baselines/common/distributions.py
stable_baselines/common/env_checker.py
stable_baselines/common/evaluation.py
stable_baselines/common/identity_env.py
stable_baselines/common/input.py
stable_baselines/common/math_util.py
stable_baselines/common/misc_util.py
stable_baselines/common/mpi_adam.py
stable_baselines/common/mpi_moments.py
stable_baselines/common/mpi_running_mean_std.py
stable_baselines/common/noise.py
stable_baselines/common/policies.py
stable_baselines/common/runners.py
stable_baselines/common/running_mean_std.py
stable_baselines/common/save_util.py
stable_baselines/common/schedules.py
stable_baselines/common/segment_tree.py
stable_baselines/common/tf_layers.py
stable_baselines/common/tf_util.py
stable_baselines/common/tile_images.py
stable_baselines/common/vec_env/__init__.py
stable_baselines/common/vec_env/base_vec_env.py
stable_baselines/common/vec_env/dummy_vec_env.py
stable_baselines/common/vec_env/subproc_vec_env.py
stable_baselines/common/vec_env/util.py
stable_baselines-2.10.1.dist-info/LICENSE
stable_baselines-2.10.1.dist-info/METADATA
stable_baselines-2.10.1.dist-info/WHEEL
stable_baselines-2.10.1.dist-info/top_level.txt
stable_baselines-2.10.1.dist-info/RECORD
