Metadata-Version: 2.1
Name: stable-baselines
Version: 2.10.1
Summary: A fork of OpenAI Baselines, implementations of reinforcement learning algorithms.
Home-page: https://github.com/hill-a/stable-baselines
Author: Ashley Hill
Author-email: ashley.hill@u-psud.fr
License: MIT
Keywords: reinforcement-learning-algorithms reinforcement-learning machine-learning gym openai baselines toolbox python data-science
Platform: UNKNOWN
Provides-Extra: mpi
Provides-Extra: tests
Provides-Extra: docs
